{
  "matches_analyzed": 10,
  "goals": 1.0,
  "xg_total": 1.44,
  "xg_per90": 0.14,
  "shots_total": 18.0,
  "shots_per90": 1.8,
  "key_passes": 8.0,
  "key_passes_per90": 0.8,
  "xA": 1.0,
  "xA_per90": 0.1,
  "passes_total": 347.0,
  "passes_completed": 275.0,
  "pass_completion_pct": 79.3,
  "progressive_passes": 78.0,
  "progressive_passes_per90": 7.8,
  "passes_final_third": 105.0,
  "passes_final_third_per90": 10.5,
  "progressive_carries": 98.0,
  "progressive_carries_per90": 9.8,
  "carry_distance_total": 2346.3,
  "carry_distance_per90": 234.6,
  "pressures": 222.0,
  "pressures_per90": 22.2,
  "duels_total": 30.0,
  "duels_won": 0.0,
  "duel_win_pct": 0.0,
  "interceptions": 9.0,
  "interceptions_per90": 0.9,
  "ball_recoveries": 36.0,
  "ball_recoveries_per90": 3.6,
  "player_name": "Blerim Džemaili",
  "percentiles": {
    "pct_xg_per90": 82.3,
    "pct_xA_per90": 80.9,
    "pct_key_passes_per90": 81.4,
    "pct_progressive_passes_per90": 42.1,
    "pct_progressive_carries_per90": 93.8,
    "pct_pressures_per90": 95.3,
    "pct_duel_win_pct": 100.0,
    "pct_interceptions_per90": 63.7,
    "pct_ball_recoveries_per90": 60.5,
    "pct_passes_final_third_per90": 77.6,
    "pct_carry_distance_per90": 90.0,
    "pct_pass_completion_pct": 62.1,
    "pct_shots_per90": 92.1
  },
  "percentile_group": "MID",
  "percentile_sample_size": 3247
}