{
  "matches_analyzed": 25,
  "goals": 0.0,
  "xg_total": 4.22,
  "xg_per90": 0.17,
  "shots_total": 35.0,
  "shots_per90": 1.4,
  "key_passes": 5.0,
  "key_passes_per90": 0.2,
  "xA": 3.0,
  "xA_per90": 0.12,
  "passes_total": 379.0,
  "passes_completed": 272.0,
  "pass_completion_pct": 71.8,
  "progressive_passes": 58.0,
  "progressive_passes_per90": 2.3,
  "passes_final_third": 134.0,
  "passes_final_third_per90": 5.4,
  "progressive_carries": 45.0,
  "progressive_carries_per90": 1.8,
  "carry_distance_total": 1689.1,
  "carry_distance_per90": 67.6,
  "pressures": 207.0,
  "pressures_per90": 8.3,
  "duels_total": 120.0,
  "duels_won": 0.0,
  "duel_win_pct": 0.0,
  "interceptions": 6.0,
  "interceptions_per90": 0.2,
  "ball_recoveries": 29.0,
  "ball_recoveries_per90": 1.2,
  "player_name": "Éderzito António Macedo Lopes",
  "percentiles": {
    "pct_xg_per90": 87.8,
    "pct_xA_per90": 86.5,
    "pct_key_passes_per90": 38.8,
    "pct_progressive_passes_per90": 11.0,
    "pct_progressive_carries_per90": 13.2,
    "pct_pressures_per90": 32.0,
    "pct_duel_win_pct": 100.0,
    "pct_interceptions_per90": 26.4,
    "pct_ball_recoveries_per90": 8.4,
    "pct_passes_final_third_per90": 47.5,
    "pct_carry_distance_per90": 16.8,
    "pct_pass_completion_pct": 31.5,
    "pct_shots_per90": 85.8
  },
  "percentile_group": "MID",
  "percentile_sample_size": 3566
}