{
  "player_name": "Éderzito António Macedo Lopes",
  "matches_analyzed": 29,
  "goals": 3,
  "xg_total": 4.37,
  "xg_per90": 0.15,
  "shots_total": 34,
  "shots_per90": 1.2,
  "key_passes": 6,
  "key_passes_per90": 0.2,
  "xA": 3.0,
  "xA_per90": 0.1,
  "passes_total": 403,
  "passes_completed": 298,
  "pass_completion_pct": 73.9,
  "progressive_passes": 64,
  "progressive_passes_per90": 2.2,
  "passes_final_third": 138,
  "passes_final_third_per90": 4.8,
  "progressive_carries": 47,
  "progressive_carries_per90": 1.6,
  "carry_distance_total": 1817.8,
  "carry_distance_per90": 62.7,
  "pressures": 219,
  "pressures_per90": 7.6,
  "duels_total": 125,
  "duels_won": 0,
  "duel_win_pct": 0.0,
  "interceptions": 6,
  "interceptions_per90": 0.2,
  "ball_recoveries": 29,
  "ball_recoveries_per90": 1.0,
  "percentiles": {
    "pct_xg_per90": 85.5,
    "pct_xA_per90": 84.3,
    "pct_key_passes_per90": 40.3,
    "pct_progressive_passes_per90": 11.2,
    "pct_progressive_carries_per90": 11.9,
    "pct_pressures_per90": 27.9,
    "pct_duel_win_pct": 100.0,
    "pct_interceptions_per90": 27.4,
    "pct_ball_recoveries_per90": 7.5,
    "pct_passes_final_third_per90": 43.9,
    "pct_carry_distance_per90": 15.7,
    "pct_pass_completion_pct": 39.5,
    "pct_shots_per90": 81.5
  },
  "percentile_group": "MID",
  "percentile_sample_size": 3759,
  "goals_note": "estimé (bug conversion données source)",
  "goals_estimated": true
}