{
  "matches_analyzed": 18,
  "goals": 0,
  "xg_total": 0.13,
  "xg_per90": 0.01,
  "shots_total": 3,
  "shots_per90": 0.2,
  "key_passes": 5,
  "key_passes_per90": 0.3,
  "xA": 0.0,
  "xA_per90": 0.0,
  "passes_total": 488,
  "passes_completed": 403,
  "pass_completion_pct": 82.6,
  "progressive_passes": 113,
  "progressive_passes_per90": 6.3,
  "passes_final_third": 62,
  "passes_final_third_per90": 3.4,
  "progressive_carries": 54,
  "progressive_carries_per90": 3.0,
  "carry_distance_total": 1725.0,
  "carry_distance_per90": 95.8,
  "pressures": 327,
  "pressures_per90": 18.2,
  "duels_total": 58,
  "duels_won": 0,
  "duel_win_pct": 0.0,
  "interceptions": 9,
  "interceptions_per90": 0.5,
  "ball_recoveries": 50,
  "ball_recoveries_per90": 2.8,
  "player_name": "Giampiero Pinzi",
  "percentiles": {
    "pct_xg_per90": 31.8,
    "pct_xA_per90": 64.6,
    "pct_key_passes_per90": 50.2,
    "pct_progressive_passes_per90": 35.7,
    "pct_progressive_carries_per90": 32.4,
    "pct_pressures_per90": 89.3,
    "pct_duel_win_pct": 100.0,
    "pct_interceptions_per90": 44.5,
    "pct_ball_recoveries_per90": 42.3,
    "pct_passes_final_third_per90": 34.2,
    "pct_carry_distance_per90": 35.0,
    "pct_pass_completion_pct": 76.1,
    "pct_shots_per90": 27.5
  },
  "percentile_group": "MID",
  "percentile_sample_size": 3759
}