{
  "player_name": "Jeremain Lens",
  "matches_analyzed": 5,
  "goals": 0,
  "xg_total": 0.26,
  "xg_per90": 0.05,
  "shots_total": 6,
  "shots_per90": 1.2,
  "key_passes": 4,
  "key_passes_per90": 0.8,
  "xA": 0.0,
  "xA_per90": 0.0,
  "passes_total": 96,
  "passes_completed": 62,
  "pass_completion_pct": 64.6,
  "progressive_passes": 44,
  "progressive_passes_per90": 8.8,
  "passes_final_third": 36,
  "passes_final_third_per90": 7.2,
  "progressive_carries": 36,
  "progressive_carries_per90": 7.2,
  "carry_distance_total": 857.0,
  "carry_distance_per90": 171.4,
  "pressures": 83,
  "pressures_per90": 16.6,
  "duels_total": 17,
  "duels_won": 0,
  "duel_win_pct": 0.0,
  "interceptions": 1,
  "interceptions_per90": 0.2,
  "ball_recoveries": 17,
  "ball_recoveries_per90": 3.4
}