{
  "matches_analyzed": 32,
  "goals": 1,
  "xg_total": 2.71,
  "xg_per90": 0.08,
  "shots_total": 47,
  "shots_per90": 1.5,
  "key_passes": 20,
  "key_passes_per90": 0.6,
  "xA": 2.0,
  "xA_per90": 0.06,
  "passes_total": 661,
  "passes_completed": 475,
  "pass_completion_pct": 71.9,
  "progressive_passes": 194,
  "progressive_passes_per90": 6.1,
  "passes_final_third": 232,
  "passes_final_third_per90": 7.2,
  "progressive_carries": 130,
  "progressive_carries_per90": 4.1,
  "carry_distance_total": 4162.8,
  "carry_distance_per90": 130.1,
  "pressures": 428,
  "pressures_per90": 13.4,
  "duels_total": 75,
  "duels_won": 0,
  "duel_win_pct": 0.0,
  "interceptions": 18,
  "interceptions_per90": 0.6,
  "ball_recoveries": 110,
  "ball_recoveries_per90": 3.4,
  "player_name": "Marco Benassi",
  "percentiles": {
    "pct_xg_per90": 71.9,
    "pct_xA_per90": 76.1,
    "pct_key_passes_per90": 72.0,
    "pct_progressive_passes_per90": 34.4,
    "pct_progressive_carries_per90": 48.8,
    "pct_pressures_per90": 69.4,
    "pct_duel_win_pct": 100.0,
    "pct_interceptions_per90": 48.9,
    "pct_ball_recoveries_per90": 56.3,
    "pct_passes_final_third_per90": 61.0,
    "pct_carry_distance_per90": 53.8,
    "pct_pass_completion_pct": 31.9,
    "pct_shots_per90": 88.5
  },
  "percentile_group": "MID",
  "percentile_sample_size": 3759,
  "goals_note": "estimé (bug conversion données source)"
}