{
  "player_name": "Nampalys Mendy",
  "matches_analyzed": 47,
  "goals": 0,
  "xg_total": 0.44,
  "xg_per90": 0.01,
  "shots_total": 13,
  "shots_per90": 0.3,
  "key_passes": 8,
  "key_passes_per90": 0.2,
  "xA": 1.0,
  "xA_per90": 0.02,
  "passes_total": 3284,
  "passes_completed": 3022,
  "pass_completion_pct": 92.0,
  "progressive_passes": 604,
  "progressive_passes_per90": 12.9,
  "passes_final_third": 168,
  "passes_final_third_per90": 3.6,
  "progressive_carries": 412,
  "progressive_carries_per90": 8.8,
  "carry_distance_total": 12805.1,
  "carry_distance_per90": 272.4,
  "pressures": 579,
  "pressures_per90": 12.3,
  "duels_total": 96,
  "duels_won": 0,
  "duel_win_pct": 0.0,
  "interceptions": 49,
  "interceptions_per90": 1.0,
  "ball_recoveries": 311,
  "ball_recoveries_per90": 6.6,
  "percentiles": {
    "pct_xg_per90": 31.8,
    "pct_xA_per90": 65.5,
    "pct_key_passes_per90": 40.3,
    "pct_progressive_passes_per90": 66.1,
    "pct_progressive_carries_per90": 91.4,
    "pct_pressures_per90": 62.4,
    "pct_duel_win_pct": 100.0,
    "pct_interceptions_per90": 69.5,
    "pct_ball_recoveries_per90": 98.4,
    "pct_passes_final_third_per90": 35.4,
    "pct_carry_distance_per90": 96.2,
    "pct_pass_completion_pct": 97.7,
    "pct_shots_per90": 36.8
  },
  "percentile_group": "MID",
  "percentile_sample_size": 3759
}