{
  "player_name": "Ricardo Iván Rodríguez Araya",
  "matches_analyzed": 29,
  "goals": 0,
  "xg_total": 1.12,
  "xg_per90": 0.04,
  "shots_total": 17,
  "shots_per90": 0.6,
  "key_passes": 25,
  "key_passes_per90": 0.9,
  "xA": 0.0,
  "xA_per90": 0.0,
  "passes_total": 1568,
  "passes_completed": 1243,
  "pass_completion_pct": 79.3,
  "progressive_passes": 558,
  "progressive_passes_per90": 19.2,
  "passes_final_third": 406,
  "passes_final_third_per90": 14.0,
  "progressive_carries": 249,
  "progressive_carries_per90": 8.6,
  "carry_distance_total": 5984.3,
  "carry_distance_per90": 206.4,
  "pressures": 299,
  "pressures_per90": 10.3,
  "duels_total": 76,
  "duels_won": 0,
  "duel_win_pct": 0.0,
  "interceptions": 16,
  "interceptions_per90": 0.6,
  "ball_recoveries": 92,
  "ball_recoveries_per90": 3.2,
  "percentiles": {
    "pct_xg_per90": 55.3,
    "pct_xA_per90": 64.6,
    "pct_key_passes_per90": 85.8,
    "pct_progressive_passes_per90": 86.5,
    "pct_progressive_carries_per90": 90.7,
    "pct_pressures_per90": 48.1,
    "pct_duel_win_pct": 100.0,
    "pct_interceptions_per90": 48.9,
    "pct_ball_recoveries_per90": 52.0,
    "pct_passes_final_third_per90": 90.7,
    "pct_carry_distance_per90": 84.9,
    "pct_pass_completion_pct": 62.9,
    "pct_shots_per90": 55.9
  },
  "percentile_group": "MID",
  "percentile_sample_size": 3759
}