{
  "matches_analyzed": 8,
  "goals": 2,
  "xg_total": 2.39,
  "xg_per90": 0.3,
  "shots_total": 23,
  "shots_per90": 2.9,
  "key_passes": 11,
  "key_passes_per90": 1.4,
  "xA": 1.0,
  "xA_per90": 0.12,
  "passes_total": 400,
  "passes_completed": 322,
  "pass_completion_pct": 80.5,
  "progressive_passes": 138,
  "progressive_passes_per90": 17.2,
  "passes_final_third": 103,
  "passes_final_third_per90": 12.9,
  "progressive_carries": 51,
  "progressive_carries_per90": 6.4,
  "carry_distance_total": 1312.1,
  "carry_distance_per90": 164.0,
  "pressures": 148,
  "pressures_per90": 18.5,
  "duels_total": 25,
  "duels_won": 0,
  "duel_win_pct": 0.0,
  "interceptions": 24,
  "interceptions_per90": 3.0,
  "ball_recoveries": 54,
  "ball_recoveries_per90": 6.8,
  "player_name": "Yohan Cabaye",
  "percentiles": {
    "pct_xg_per90": 95.5,
    "pct_xA_per90": 84.6,
    "pct_key_passes_per90": 95.0,
    "pct_progressive_passes_per90": 81.6,
    "pct_progressive_carries_per90": 74.9,
    "pct_pressures_per90": 88.4,
    "pct_duel_win_pct": 100.0,
    "pct_interceptions_per90": 99.5,
    "pct_ball_recoveries_per90": 97.9,
    "pct_passes_final_third_per90": 87.1,
    "pct_carry_distance_per90": 67.5,
    "pct_pass_completion_pct": 67.1,
    "pct_shots_per90": 98.5
  },
  "percentile_group": "MID",
  "percentile_sample_size": 3247
}